xy_singleton/Decorators.py
xy_singleton/Singleton.py
xy_singleton/__init__.py
xy_singleton-1.0.2.dist-info/LICENSE
xy_singleton-1.0.2.dist-info/METADATA
xy_singleton-1.0.2.dist-info/WHEEL
xy_singleton-1.0.2.dist-info/top_level.txt
xy_singleton-1.0.2.dist-info/RECORD
