Metadata-Version: 2.1
Name: xy_singleton
Version: 1.0.2
Summary: Python单例的几种实现方式
Author-email: yuyangit <yuyangit.0515@qq.com>
Classifier: Programming Language :: Python :: 3
Requires-Python: >=3.11.3
License-File: LICENSE
